fastc/__init__.py
fastc/fastc.py
fastc/kernels.py
fastc/pooling.py
fastc/template.py
fastc/classifiers/centroids.py
fastc/classifiers/embeddings.py
fastc/classifiers/interface.py
fastc/classifiers/loader.py
fastc/classifiers/logistic_regression.py
fastc-2.2407.0.dist-info/LICENSE
fastc-2.2407.0.dist-info/METADATA
fastc-2.2407.0.dist-info/WHEEL
fastc-2.2407.0.dist-info/top_level.txt
fastc-2.2407.0.dist-info/RECORD
