Metadata-Version: 2.1
Name: fastc
Version: 2.2407.0
Summary: Unattended Lightweight Text Classifiers with State-of-the-Art LLM Embeddings
Author-email: "Rodrigo Martínez (brunneis)" <dev@brunneis.com>
License: GNU General Public License v3 (GPLv3)
Project-URL: Repository, https://github.com/EveripediaNetwork/fastc
Classifier: Development Status :: 4 - Beta
Classifier: Environment :: Console
Classifier: Intended Audience :: Developers
Classifier: License :: OSI Approved :: GNU General Public License v3 (GPLv3)
Classifier: Operating System :: POSIX :: Linux
Classifier: Programming Language :: Python :: 3.10
Classifier: Programming Language :: Python :: Implementation :: PyPy
Classifier: Topic :: Software Development :: Libraries :: Python Modules
Requires-Python: >=3.10
License-File: LICENSE
Requires-Dist: transformers
Requires-Dist: huggingface-hub
Requires-Dist: torch
Requires-Dist: tqdm
Requires-Dist: scikit-learn
Requires-Dist: joblib
Provides-Extra: dev
Requires-Dist: build ; extra == 'dev'
Requires-Dist: installer ; extra == 'dev'
Requires-Dist: wheel ; extra == 'dev'
Requires-Dist: twine ; extra == 'dev'
